md_star/__about__.py
md_star/__init__.py
md_star/cli.py
md_star/config.yaml
md_star/generator.py
md_star/requirements.txt
md_star/content/Hello.md
md_star/public/favicon.ico
md_star/public/robots.txt
md_star/templates/about.html
md_star/templates/base.html
md_star/templates/index.html
md_star/templates/post.html
md_star/templates/components/x_card.html
md_star-0.0.7.dist-info/METADATA
md_star-0.0.7.dist-info/WHEEL
md_star-0.0.7.dist-info/entry_points.txt
md_star-0.0.7.dist-info/licenses/LICENSE.txt
md_star-0.0.7.dist-info/RECORD
