Metadata-Version: 2.4
Name: md-star
Version: 0.0.7
Summary: A Markdown Static Site Generator.
Project-URL: Documentation, https://github.com/chris1ding1/md-star#readme
Project-URL: Issues, https://github.com/chris1ding1/md-star/issues
Project-URL: Source, https://github.com/chris1ding1/md-star
Author-email: chris <chris1ding1@gmail.com>
License-Expression: MIT
License-File: LICENSE.txt
Keywords: Blog,CMS,HTML,Markdown,Static Site Generator,Website
Classifier: Development Status :: 4 - Beta
Classifier: Programming Language :: Python
Classifier: Programming Language :: Python :: 3.8
Classifier: Programming Language :: Python :: 3.9
Classifier: Programming Language :: Python :: 3.10
Classifier: Programming Language :: Python :: 3.11
Classifier: Programming Language :: Python :: 3.12
Classifier: Programming Language :: Python :: Implementation :: CPython
Classifier: Programming Language :: Python :: Implementation :: PyPy
Requires-Python: <3.13,>=3.8
Requires-Dist: arrow
Requires-Dist: click
Requires-Dist: jinja2
Requires-Dist: markdown
Requires-Dist: markdown-it-py
Requires-Dist: markupsafe
Requires-Dist: pymdown-extensions
Requires-Dist: python-frontmatter
Requires-Dist: python-slugify
Requires-Dist: pyyaml
Requires-Dist: text-unidecode
